LICENSE
MANIFEST.in
README.txt
setup.py
cameo/__init__.py
cameo/cameoshell.py
cameo/cleaner.py
cameo/clipboardtool.py
cameo/externaldb.py
cameo/launcher.py
cameo/localdb.py
cameo/parserForBNEXT.py
cameo/parserForINDIEGOGO.py
cameo/parserForPEDAILY.py
cameo/parserForTECHORANGE.py
cameo/parserForWEBACKERS.py
cameo/parserV2ForINDIEGOGO.py
cameo/reporter.py
cameo/spiderForBNEXT.py
cameo/spiderForINDIEGOGO.py
cameo/spiderForPEDAILY.py
cameo/spiderForTECHORANGE.py
cameo/spiderForWEBACKERS.py
cameo/utility.py
cameo/mod/__init__.py
cameo/mod/yuwei/__init__.py
cameo/mod/yuwei/utility/__init__.py
cameo/mod/yuwei/utility/fileUtility.py
cameo/mod/yuwei/utility/ftpUtility.py
cameo/mod/yuwei/utility/geonameHelper.py
cameo/mod/yuwei/utility/geonames.py
cameo/mod/yuwei/utility/jsonToCsvConverter.py
cameo/mod/yuwei/utility/mailHelper.py
cameo/mod/yuwei/utility/progressBar.py
cameo/mod/yuwei/utility/scrapyUtility.py
cameo/mod/yuwei/utility/seleniumUtility.py
cameo/ui/__init__.py
cameo_api/__init__.py
cameo_api/__init__.pyc
cameo_api/apis.py
cameo_api/apis.pyc
cameo_api/flaskrunner.py
cameo_api/flaskrunner.pyc
cameo_api/ghostdriver.log
cameo_api/spiderForTwExchangeRates.py
cameo_api/spiderForTwExchangeRates.pyc
cameo_api/spiderForYahooCurrency.py
cameo_api/spiderForYahooCurrency.pyc
cameo_res/__init__.py
cameo_res/chromedriver.exe
cameo_res/icon.ico
cameo_res/iso_3166_1_on_wikipedia.html
cameo_res/list_of_country_by_continent_on_wikipedia.html
cameo_res/phantomjs.exe
cameo_res/parsed_result/__init__.py
cameo_res/source_html/__init__.py
pycameo.egg-info/PKG-INFO
pycameo.egg-info/SOURCES.txt
pycameo.egg-info/dependency_links.txt
pycameo.egg-info/entry_points.txt
pycameo.egg-info/requires.txt
pycameo.egg-info/top_level.txt