Metadata-Version: 1.1
Name: pycameo
Version: 0.1.2a1
Summary: cameo scrapy project
Home-page: https://github.com/muchu1983/104_cameo
Author: MuChu Hsu
Author-email: muchu1983@gmail.com
License: BSD 3-Clause License
Download-URL: https://pypi.python.org/pypi/cameo
Platform: python 2.7
Classifier: Development Status :: 3 - Alpha
Classifier: Environment :: Win32 (MS Windows)
Classifier: Environment :: X11 Applications :: GTK
Classifier: Intended Audience :: End Users/Desktop
Classifier: Intended Audience :: Developers
Classifier: License :: OSI Approved :: BSD License
Classifier: Natural Language :: Chinese (Traditional)
Classifier: Natural Language :: Chinese (Simplified)
Classifier: Natural Language :: English
Classifier: Operating System :: Microsoft :: Windows
Classifier: Operating System :: POSIX :: Linux
Classifier: Programming Language :: Python :: 2.7
Classifier: Topic :: Internet :: WWW/HTTP
Classifier: Topic :: Multimedia :: Graphics :: Viewers
